src/firewall.sv
`default_nettype none
`timescale 1ns / 1ps

module firewall(
    input wire clk,
    input wire rst,
    input wire axiiv,
    input wire [1:0] axiid,
    output logic axiov,
    output logic [1:0] axiod
);
    parameter MAC_ADDRESS = 48'h69_69_5A_06_54_91;
    parameter BROADCAST = 48'hFF_FF_FF_FF_FF_FF;

    typedef enum {WAITING, READING_DEST, READING_BROADCAST, READING_SRC, VALID_DEST, INVALID_DEST}  firewall_state;
    firewall_state state;

    logic [47:0] mac_buffer;
    logic [4:0] count;

    assign axiod = axiid;
    assign axiov = (state == VALID_DEST) & axiiv;

    always_ff @( posedge clk ) begin 
        if (rst) begin
            state <= WAITING;
            mac_buffer <= MAC_ADDRESS;
            count <= 0;
        end else begin
            case (state)
                WAITING: begin
                    if (axiiv) begin
                        if (axiid == MAC_ADDRESS[47:46]) begin
                            state <= READING_DEST;
                            mac_buffer <= {MAC_ADDRESS[45:0], 2'b00};
                            count <= 1;
                        end else if (axiid == 2'b11) begin
                            state <= READING_BROADCAST;
                            count <= 1;
                        end else begin
                            state <= INVALID_DEST;
                        end
                    end
                end
                READING_DEST: begin
                    if (axiiv) begin
                        if (axiid == mac_buffer[47:46]) begin
                            mac_buffer <= {mac_buffer[45:0], 2'b00};
                            if (count == 5'd23) begin
                                count <= 0;
                                state <= READING_SRC;
                            end else begin
                                count <= count + 1;
                            end
                        end else begin
                            state <= INVALID_DEST;
                        end
                    end else begin
                        state <= WAITING;
                    end
                end
                READING_BROADCAST: begin
                    if (axiiv) begin
                        if (axiid == 2'b11) begin
                            if (count == 5'd23) begin
                                count <= 0;
                                state <= READING_SRC;
                            end else begin
                                count <= count + 1;
                            end
                        end else begin
                            state <= INVALID_DEST;
                        end
                    end else begin
                        state <= WAITING;
                    end
                end
                READING_SRC: begin
                    if (axiiv) begin
                        if (count == 5'd31) begin
                            count <= 0;
                            state <= VALID_DEST;
                        end else begin
                            count <= count+1;
                        end
                    end else begin
                        state <= WAITING;
                    end
                end
                VALID_DEST: begin
                    if (~axiiv) begin
                        state <= WAITING;
                    end
                end
                INVALID_DEST: begin
                    if (~axiiv) begin
                        state <= WAITING;
                    end
                end
            endcase
        end
    end

endmodule

`default_nettype wire

sim/firewall_tb.sv
`default_nettype none
`timescale 1ns / 1ps

module firewall_tb;

    logic clk;
    logic rst;
    logic axiiv;
    logic [1:0] axiid;
    logic axiov;
    logic [1:0] axiod;
    logic [47:0] addr;

    firewall fw(
        .clk(clk),
        .rst(rst),
        .axiiv(axiiv),
        .axiid(axiid),
        .axiov(axiov),
        .axiod(axiod)
    );

    // 50 MHz clock
    always begin
        #10;
        clk = !clk;
    end

    initial begin
        $dumpfile("firewall.vcd");
        $dumpvars(0, firewall_tb);
        $display("Starting Sim");

        clk = 1'b0;
        rst = 1'b0;
        axiiv = 1'b0;
        axiid = 32'b0;
        #20;
        #20;
        rst = 1'b1;
        #20;
        rst = 1'b0;
        #20;
        #20;

        // TC1: garbage MAC

        // dest
        for (integer i = 0; i < 24; i= i+1) begin
            axiiv = 1'b1;
            axiid = 2'b01;
            #20;
        end

        //src + length
        for (integer i = 0; i < 32; i= i+1) begin
            axiiv = 1'b1;
            axiid = 2'b00;
            #20;
        end

        // data + fcs
        for (integer i = 0; i < 100; i= i+1) begin
            axiiv = 1'b1;
            axiid = 2'b10;
            #20;
        end

        axiiv = 1'b0;
        #400;

        // TC2: global

        // dest
        for (integer i = 0; i < 24; i= i+1) begin
            axiiv = 1'b1;
            axiid = 2'b11;
            #20;
        end

        //src + length
        for (integer i = 0; i < 32; i= i+1) begin
            axiiv = 1'b1;
            axiid = 2'b00;
            #20;
        end

        // data + fcs
        for (integer i = 0; i < 100; i= i+1) begin
            axiiv = 1'b1;
            axiid = 2'b10;
            #20;
        end

        axiiv = 1'b0;
        #400;

        // TC3: specific

        // dest
        addr = 48'h69_69_5A_06_54_91;
        for (integer i = 0; i < 24; i= i+1) begin
            axiiv = 1'b1;
            axiid = addr[47:46];
            addr = {addr[45:0], addr[47:46]};
            #20;
        end

        //src + length
        for (integer i = 0; i < 32; i= i+1) begin
            axiiv = 1'b1;
            axiid = 2'b00;
            #20;
        end

        // data + fcs
        for (integer i = 0; i < 100; i= i+1) begin
            axiiv = 1'b1;
            axiid = 2'b10;
            #20;
        end

        axiiv = 1'b0;
        #400;

        $display("\nFinishing Sim");
        $finish;
    end
endmodule

`default_nettype wire

firewall.vcd
$date
	Thu Oct 27 16:53:48 2022
$end
$version
	Icarus Verilog
$end
$timescale
	1ps
$end
$scope module firewall_tb $end
$var wire 1 ! axiov $end
$var wire 2 " axiod [1:0] $end
$var reg 48 # addr [47:0] $end
$var reg 2 $ axiid [1:0] $end
$var reg 1 % axiiv $end
$var reg 1 & clk $end
$var reg 1 ' rst $end
$scope module fw $end
$var wire 2 ( axiid [1:0] $end
$var wire 1 % axiiv $end
$var wire 2 ) axiod [1:0] $end
$var wire 1 ! axiov $end
$var wire 1 & clk $end
$var wire 1 ' rst $end
$var reg 5 * count [4:0] $end
$var reg 48 + mac_buffer [47:0] $end
$var integer 32 , state [31:0] $end
$upscope $end
$scope begin $ivl_for_loop0 $end
$var integer 32 - i [31:0] $end
$upscope $end
$scope begin $ivl_for_loop1 $end
$var integer 32 . i [31:0] $end
$upscope $end
$scope begin $ivl_for_loop2 $end
$var integer 32 / i [31:0] $end
$upscope $end
$scope begin $ivl_for_loop3 $end
$var integer 32 0 i [31:0] $end
$upscope $end
$scope begin $ivl_for_loop4 $end
$var integer 32 1 i [31:0] $end
$upscope $end
$scope begin $ivl_for_loop5 $end
$var integer 32 2 i [31:0] $end
$upscope $end
$scope begin $ivl_for_loop6 $end
$var integer 32 3 i [31:0] $end
$upscope $end
$scope begin $ivl_for_loop7 $end
$var integer 32 4 i [31:0] $end
$upscope $end
$scope begin $ivl_for_loop8 $end
$var integer 32 5 i [31:0] $end
$upscope $end
$upscope $end
$enddefinitions $end
#0
$dumpvars
bx 5
bx 4
bx 3
bx 2
bx 1
bx 0
bx /
bx .
bx -
b0 ,
bx +
bx *
b0 )
b0 (
0'
0&
0%
b0 $
bx #
b0 "
0!
$end
#10000
1&
#20000
0&
#30000
1&
#40000
0&
1'
#50000
b0 *
b11010010110100101011010000001100101010010010001 +
1&
#60000
0&
0'
#70000
1&
#80000
0&
#90000
1&
#100000
0&
b1 "
b1 )
b1 $
b1 (
1%
b0 -
#110000
b1 *
b101001011010010101101000000110010101001001000100 +
b1 ,
1&
#120000
0&
b1 -
#130000
b101 ,
1&
#140000
0&
b10 -
#150000
1&
#160000
0&
b11 -
#170000
1&
#180000
0&
b100 -
#190000
1&
#200000
0&
b101 -
#210000
1&
#220000
0&
b110 -
#230000
1&
#240000
0&
b111 -
#250000
1&
#260000
0&
b1000 -
#270000
1&
#280000
0&
b1001 -
#290000
1&
#300000
0&
b1010 -
#310000
1&
#320000
0&
b1011 -
#330000
1&
#340000
0&
b1100 -
#350000
1&
#360000
0&
b1101 -
#370000
1&
#380000
0&
b1110 -
#390000
1&
#400000
0&
b1111 -
#410000
1&
#420000
0&
b10000 -
#430000
1&
#440000
0&
b10001 -
#450000
1&
#460000
0&
b10010 -
#470000
1&
#480000
0&
b10011 -
#490000
1&
#500000
0&
b10100 -
#510000
1&
#520000
0&
b10101 -
#530000
1&
#540000
0&
b10110 -
#550000
1&
#560000
0&
b10111 -
#570000
1&
#580000
0&
b0 "
b0 )
b0 $
b0 (
b0 .
b11000 -
#590000
1&
#600000
0&
b1 .
#610000
1&
#620000
0&
b10 .
#630000
1&
#640000
0&
b11 .
#650000
1&
#660000
0&
b100 .
#670000
1&
#680000
0&
b101 .
#690000
1&
#700000
0&
b110 .
#710000
1&
#720000
0&
b111 .
#730000
1&
#740000
0&
b1000 .
#750000
1&
#760000
0&
b1001 .
#770000
1&
#780000
0&
b1010 .
#790000
1&
#800000
0&
b1011 .
#810000
1&
#820000
0&
b1100 .
#830000
1&
#840000
0&
b1101 .
#850000
1&
#860000
0&
b1110 .
#870000
1&
#880000
0&
b1111 .
#890000
1&
#900000
0&
b10000 .
#910000
1&
#920000
0&
b10001 .
#930000
1&
#940000
0&
b10010 .
#950000
1&
#960000
0&
b10011 .
#970000
1&
#980000
0&
b10100 .
#990000
1&
#1000000
0&
b10101 .
#1010000
1&
#1020000
0&
b10110 .
#1030000
1&
#1040000
0&
b10111 .
#1050000
1&
#1060000
0&
b11000 .
#1070000
1&
#1080000
0&
b11001 .
#1090000
1&
#1100000
0&
b11010 .
#1110000
1&
#1120000
0&
b11011 .
#1130000
1&
#1140000
0&
b11100 .
#1150000
1&
#1160000
0&
b11101 .
#1170000
1&
#1180000
0&
b11110 .
#1190000
1&
#1200000
0&
b11111 .
#1210000
1&
#1220000
0&
b10 "
b10 )
b10 $
b10 (
b0 /
b100000 .
#1230000
1&
#1240000
0&
b1 /
#1250000
1&
#1260000
0&
b10 /
#1270000
1&
#1280000
0&
b11 /
#1290000
1&
#1300000
0&
b100 /
#1310000
1&
#1320000
0&
b101 /
#1330000
1&
#1340000
0&
b110 /
#1350000
1&
#1360000
0&
b111 /
#1370000
1&
#1380000
0&
b1000 /
#1390000
1&
#1400000
0&
b1001 /
#1410000
1&
#1420000
0&
b1010 /
#1430000
1&
#1440000
0&
b1011 /
#1450000
1&
#1460000
0&
b1100 /
#1470000
1&
#1480000
0&
b1101 /
#1490000
1&
#1500000
0&
b1110 /
#1510000
1&
#1520000
0&
b1111 /
#1530000
1&
#1540000
0&
b10000 /
#1550000
1&
#1560000
0&
b10001 /
#1570000
1&
#1580000
0&
b10010 /
#1590000
1&
#1600000
0&
b10011 /
#1610000
1&
#1620000
0&
b10100 /
#1630000
1&
#1640000
0&
b10101 /
#1650000
1&
#1660000
0&
b10110 /
#1670000
1&
#1680000
0&
b10111 /
#1690000
1&
#1700000
0&
b11000 /
#1710000
1&
#1720000
0&
b11001 /
#1730000
1&
#1740000
0&
b11010 /
#1750000
1&
#1760000
0&
b11011 /
#1770000
1&
#1780000
0&
b11100 /
#1790000
1&
#1800000
0&
b11101 /
#1810000
1&
#1820000
0&
b11110 /
#1830000
1&
#1840000
0&
b11111 /
#1850000
1&
#1860000
0&
b100000 /
#1870000
1&
#1880000
0&
b100001 /
#1890000
1&
#1900000
0&
b100010 /
#1910000
1&
#1920000
0&
b100011 /
#1930000
1&
#1940000
0&
b100100 /
#1950000
1&
#1960000
0&
b100101 /
#1970000
1&
#1980000
0&
b100110 /
#1990000
1&
#2000000
0&
b100111 /
#2010000
1&
#2020000
0&
b101000 /
#2030000
1&
#2040000
0&
b101001 /
#2050000
1&
#2060000
0&
b101010 /
#2070000
1&
#2080000
0&
b101011 /
#2090000
1&
#2100000
0&
b101100 /
#2110000
1&
#2120000
0&
b101101 /
#2130000
1&
#2140000
0&
b101110 /
#2150000
1&
#2160000
0&
b101111 /
#2170000
1&
#2180000
0&
b110000 /
#2190000
1&
#2200000
0&
b110001 /
#2210000
1&
#2220000
0&
b110010 /
#2230000
1&
#2240000
0&
b110011 /
#2250000
1&
#2260000
0&
b110100 /
#2270000
1&
#2280000
0&
b110101 /
#2290000
1&
#2300000
0&
b110110 /
#2310000
1&
#2320000
0&
b110111 /
#2330000
1&
#2340000
0&
b111000 /
#2350000
1&
#2360000
0&
b111001 /
#2370000
1&
#2380000
0&
b111010 /
#2390000
1&
#2400000
0&
b111011 /
#2410000
1&
#2420000
0&
b111100 /
#2430000
1&
#2440000
0&
b111101 /
#2450000
1&
#2460000
0&
b111110 /
#2470000
1&
#2480000
0&
b111111 /
#2490000
1&
#2500000
0&
b1000000 /
#2510000
1&
#2520000
0&
b1000001 /
#2530000
1&
#2540000
0&
b1000010 /
#2550000
1&
#2560000
0&
b1000011 /
#2570000
1&
#2580000
0&
b1000100 /
#2590000
1&
#2600000
0&
b1000101 /
#2610000
1&
#2620000
0&
b1000110 /
#2630000
1&
#2640000
0&
b1000111 /
#2650000
1&
#2660000
0&
b1001000 /
#2670000
1&
#2680000
0&
b1001001 /
#2690000
1&
#2700000
0&
b1001010 /
#2710000
1&
#2720000
0&
b1001011 /
#2730000
1&
#2740000
0&
b1001100 /
#2750000
1&
#2760000
0&
b1001101 /
#2770000
1&
#2780000
0&
b1001110 /
#2790000
1&
#2800000
0&
b1001111 /
#2810000
1&
#2820000
0&
b1010000 /
#2830000
1&
#2840000
0&
b1010001 /
#2850000
1&
#2860000
0&
b1010010 /
#2870000
1&
#2880000
0&
b1010011 /
#2890000
1&
#2900000
0&
b1010100 /
#2910000
1&
#2920000
0&
b1010101 /
#2930000
1&
#2940000
0&
b1010110 /
#2950000
1&
#2960000
0&
b1010111 /
#2970000
1&
#2980000
0&
b1011000 /
#2990000
1&
#3000000
0&
b1011001 /
#3010000
1&
#3020000
0&
b1011010 /
#3030000
1&
#3040000
0&
b1011011 /
#3050000
1&
#3060000
0&
b1011100 /
#3070000
1&
#3080000
0&
b1011101 /
#3090000
1&
#3100000
0&
b1011110 /
#3110000
1&
#3120000
0&
b1011111 /
#3130000
1&
#3140000
0&
b1100000 /
#3150000
1&
#3160000
0&
b1100001 /
#3170000
1&
#3180000
0&
b1100010 /
#3190000
1&
#3200000
0&
b1100011 /
#3210000
1&
#3220000
0&
0%
b1100100 /
#3230000
b0 ,
1&
#3240000
0&
#3250000
1&
#3260000
0&
#3270000
1&
#3280000
0&
#3290000
1&
#3300000
0&
#3310000
1&
#3320000
0&
#3330000
1&
#3340000
0&
#3350000
1&
#3360000
0&
#3370000
1&
#3380000
0&
#3390000
1&
#3400000
0&
#3410000
1&
#3420000
0&
#3430000
1&
#3440000
0&
#3450000
1&
#3460000
0&
#3470000
1&
#3480000
0&
#3490000
1&
#3500000
0&
#3510000
1&
#3520000
0&
#3530000
1&
#3540000
0&
#3550000
1&
#3560000
0&
#3570000
1&
#3580000
0&
#3590000
1&
#3600000
0&
#3610000
1&
#3620000
0&
b11 "
b11 )
b11 $
b11 (
1%
b0 0
#3630000
b10 ,
1&
#3640000
0&
b1 0
#3650000
b10 *
1&
#3660000
0&
b10 0
#3670000
b11 *
1&
#3680000
0&
b11 0
#3690000
b100 *
1&
#3700000
0&
b100 0
#3710000
b101 *
1&
#3720000
0&
b101 0
#3730000
b110 *
1&
#3740000
0&
b110 0
#3750000
b111 *
1&
#3760000
0&
b111 0
#3770000
b1000 *
1&
#3780000
0&
b1000 0
#3790000
b1001 *
1&
#3800000
0&
b1001 0
#3810000
b1010 *
1&
#3820000
0&
b1010 0
#3830000
b1011 *
1&
#3840000
0&
b1011 0
#3850000
b1100 *
1&
#3860000
0&
b1100 0
#3870000
b1101 *
1&
#3880000
0&
b1101 0
#3890000
b1110 *
1&
#3900000
0&
b1110 0
#3910000
b1111 *
1&
#3920000
0&
b1111 0
#3930000
b10000 *
1&
#3940000
0&
b10000 0
#3950000
b10001 *
1&
#3960000
0&
b10001 0
#3970000
b10010 *
1&
#3980000
0&
b10010 0
#3990000
b10011 *
1&
#4000000
0&
b10011 0
#4010000
b10100 *
1&
#4020000
0&
b10100 0
#4030000
b10101 *
1&
#4040000
0&
b10101 0
#4050000
b10110 *
1&
#4060000
0&
b10110 0
#4070000
b10111 *
1&
#4080000
0&
b10111 0
#4090000
b11 ,
b0 *
1&
#4100000
0&
b0 "
b0 )
b0 $
b0 (
b0 1
b11000 0
#4110000
b1 *
1&
#4120000
0&
b1 1
#4130000
b10 *
1&
#4140000
0&
b10 1
#4150000
b11 *
1&
#4160000
0&
b11 1
#4170000
b100 *
1&
#4180000
0&
b100 1
#4190000
b101 *
1&
#4200000
0&
b101 1
#4210000
b110 *
1&
#4220000
0&
b110 1
#4230000
b111 *
1&
#4240000
0&
b111 1
#4250000
b1000 *
1&
#4260000
0&
b1000 1
#4270000
b1001 *
1&
#4280000
0&
b1001 1
#4290000
b1010 *
1&
#4300000
0&
b1010 1
#4310000
b1011 *
1&
#4320000
0&
b1011 1
#4330000
b1100 *
1&
#4340000
0&
b1100 1
#4350000
b1101 *
1&
#4360000
0&
b1101 1
#4370000
b1110 *
1&
#4380000
0&
b1110 1
#4390000
b1111 *
1&
#4400000
0&
b1111 1
#4410000
b10000 *
1&
#4420000
0&
b10000 1
#4430000
b10001 *
1&
#4440000
0&
b10001 1
#4450000
b10010 *
1&
#4460000
0&
b10010 1
#4470000
b10011 *
1&
#4480000
0&
b10011 1
#4490000
b10100 *
1&
#4500000
0&
b10100 1
#4510000
b10101 *
1&
#4520000
0&
b10101 1
#4530000
b10110 *
1&
#4540000
0&
b10110 1
#4550000
b10111 *
1&
#4560000
0&
b10111 1
#4570000
b11000 *
1&
#4580000
0&
b11000 1
#4590000
b11001 *
1&
#4600000
0&
b11001 1
#4610000
b11010 *
1&
#4620000
0&
b11010 1
#4630000
b11011 *
1&
#4640000
0&
b11011 1
#4650000
b11100 *
1&
#4660000
0&
b11100 1
#4670000
b11101 *
1&
#4680000
0&
b11101 1
#4690000
b11110 *
1&
#4700000
0&
b11110 1
#4710000
b11111 *
1&
#4720000
0&
b11111 1
#4730000
1!
b100 ,
b0 *
1&
#4740000
0&
b10 "
b10 )
b10 $
b10 (
b0 2
b100000 1
#4750000
1&
#4760000
0&
b1 2
#4770000
1&
#4780000
0&
b10 2
#4790000
1&
#4800000
0&
b11 2
#4810000
1&
#4820000
0&
b100 2
#4830000
1&
#4840000
0&
b101 2
#4850000
1&
#4860000
0&
b110 2
#4870000
1&
#4880000
0&
b111 2
#4890000
1&
#4900000
0&
b1000 2
#4910000
1&
#4920000
0&
b1001 2
#4930000
1&
#4940000
0&
b1010 2
#4950000
1&
#4960000
0&
b1011 2
#4970000
1&
#4980000
0&
b1100 2
#4990000
1&
#5000000
0&
b1101 2
#5010000
1&
#5020000
0&
b1110 2
#5030000
1&
#5040000
0&
b1111 2
#5050000
1&
#5060000
0&
b10000 2
#5070000
1&
#5080000
0&
b10001 2
#5090000
1&
#5100000
0&
b10010 2
#5110000
1&
#5120000
0&
b10011 2
#5130000
1&
#5140000
0&
b10100 2
#5150000
1&
#5160000
0&
b10101 2
#5170000
1&
#5180000
0&
b10110 2
#5190000
1&
#5200000
0&
b10111 2
#5210000
1&
#5220000
0&
b11000 2
#5230000
1&
#5240000
0&
b11001 2
#5250000
1&
#5260000
0&
b11010 2
#5270000
1&
#5280000
0&
b11011 2
#5290000
1&
#5300000
0&
b11100 2
#5310000
1&
#5320000
0&
b11101 2
#5330000
1&
#5340000
0&
b11110 2
#5350000
1&
#5360000
0&
b11111 2
#5370000
1&
#5380000
0&
b100000 2
#5390000
1&
#5400000
0&
b100001 2
#5410000
1&
#5420000
0&
b100010 2
#5430000
1&
#5440000
0&
b100011 2
#5450000
1&
#5460000
0&
b100100 2
#5470000
1&
#5480000
0&
b100101 2
#5490000
1&
#5500000
0&
b100110 2
#5510000
1&
#5520000
0&
b100111 2
#5530000
1&
#5540000
0&
b101000 2
#5550000
1&
#5560000
0&
b101001 2
#5570000
1&
#5580000
0&
b101010 2
#5590000
1&
#5600000
0&
b101011 2
#5610000
1&
#5620000
0&
b101100 2
#5630000
1&
#5640000
0&
b101101 2
#5650000
1&
#5660000
0&
b101110 2
#5670000
1&
#5680000
0&
b101111 2
#5690000
1&
#5700000
0&
b110000 2
#5710000
1&
#5720000
0&
b110001 2
#5730000
1&
#5740000
0&
b110010 2
#5750000
1&
#5760000
0&
b110011 2
#5770000
1&
#5780000
0&
b110100 2
#5790000
1&
#5800000
0&
b110101 2
#5810000
1&
#5820000
0&
b110110 2
#5830000
1&
#5840000
0&
b110111 2
#5850000
1&
#5860000
0&
b111000 2
#5870000
1&
#5880000
0&
b111001 2
#5890000
1&
#5900000
0&
b111010 2
#5910000
1&
#5920000
0&
b111011 2
#5930000
1&
#5940000
0&
b111100 2
#5950000
1&
#5960000
0&
b111101 2
#5970000
1&
#5980000
0&
b111110 2
#5990000
1&
#6000000
0&
b111111 2
#6010000
1&
#6020000
0&
b1000000 2
#6030000
1&
#6040000
0&
b1000001 2
#6050000
1&
#6060000
0&
b1000010 2
#6070000
1&
#6080000
0&
b1000011 2
#6090000
1&
#6100000
0&
b1000100 2
#6110000
1&
#6120000
0&
b1000101 2
#6130000
1&
#6140000
0&
b1000110 2
#6150000
1&
#6160000
0&
b1000111 2
#6170000
1&
#6180000
0&
b1001000 2
#6190000
1&
#6200000
0&
b1001001 2
#6210000
1&
#6220000
0&
b1001010 2
#6230000
1&
#6240000
0&
b1001011 2
#6250000
1&
#6260000
0&
b1001100 2
#6270000
1&
#6280000
0&
b1001101 2
#6290000
1&
#6300000
0&
b1001110 2
#6310000
1&
#6320000
0&
b1001111 2
#6330000
1&
#6340000
0&
b1010000 2
#6350000
1&
#6360000
0&
b1010001 2
#6370000
1&
#6380000
0&
b1010010 2
#6390000
1&
#6400000
0&
b1010011 2
#6410000
1&
#6420000
0&
b1010100 2
#6430000
1&
#6440000
0&
b1010101 2
#6450000
1&
#6460000
0&
b1010110 2
#6470000
1&
#6480000
0&
b1010111 2
#6490000
1&
#6500000
0&
b1011000 2
#6510000
1&
#6520000
0&
b1011001 2
#6530000
1&
#6540000
0&
b1011010 2
#6550000
1&
#6560000
0&
b1011011 2
#6570000
1&
#6580000
0&
b1011100 2
#6590000
1&
#6600000
0&
b1011101 2
#6610000
1&
#6620000
0&
b1011110 2
#6630000
1&
#6640000
0&
b1011111 2
#6650000
1&
#6660000
0&
b1100000 2
#6670000
1&
#6680000
0&
b1100001 2
#6690000
1&
#6700000
0&
b1100010 2
#6710000
1&
#6720000
0&
b1100011 2
#6730000
1&
#6740000
0!
0&
0%
b1100100 2
#6750000
b0 ,
1&
#6760000
0&
#6770000
1&
#6780000
0&
#6790000
1&
#6800000
0&
#6810000
1&
#6820000
0&
#6830000
1&
#6840000
0&
#6850000
1&
#6860000
0&
#6870000
1&
#6880000
0&
#6890000
1&
#6900000
0&
#6910000
1&
#6920000
0&
#6930000
1&
#6940000
0&
#6950000
1&
#6960000
0&
#6970000
1&
#6980000
0&
#6990000
1&
#7000000
0&
#7010000
1&
#7020000
0&
#7030000
1&
#7040000
0&
#7050000
1&
#7060000
0&
#7070000
1&
#7080000
0&
#7090000
1&
#7100000
0&
#7110000
1&
#7120000
0&
#7130000
1&
#7140000
0&
b1 "
b1 )
b1 $
b1 (
1%
b0 3
b101001011010010101101000000110010101001001000101 #
#7150000
b1 *
b1 ,
1&
#7160000
0&
b100101101001010110100000011001010100100100010110 #
b10 "
b10 )
b10 $
b10 (
b1 3
#7170000
b10 *
b100101101001010110100000011001010100100100010000 +
1&
#7180000
0&
b10110100101011010000001100101010010010001011010 #
b10 3
#7190000
b11 *
b10110100101011010000001100101010010010001000000 +
1&
#7200000
0&
b11010010101101000000110010101001001000101101001 #
b1 "
b1 )
b1 $
b1 (
b11 3
#7210000
b100 *
b11010010101101000000110010101001001000100000000 +
1&
#7220000
0&
b101001010110100000011001010100100100010110100101 #
b100 3
#7230000
b101 *
b101001010110100000011001010100100100010000000000 +
1&
#7240000
0&
b100101011010000001100101010010010001011010010110 #
b10 "
b10 )
b10 $
b10 (
b101 3
#7250000
b110 *
b100101011010000001100101010010010001000000000000 +
1&
#7260000
0&
b10101101000000110010101001001000101101001011010 #
b110 3
#7270000
b111 *
b10101101000000110010101001001000100000000000000 +
1&
#7280000
0&
b10110100000011001010100100100010110100101101001 #
b1 "
b1 )
b1 $
b1 (
b111 3
#7290000
b1000 *
b10110100000011001010100100100010000000000000000 +
1&
#7300000
0&
b11010000001100101010010010001011010010110100101 #
b1000 3
#7310000
b1001 *
b11010000001100101010010010001000000000000000000 +
1&
#7320000
0&
b101000000110010101001001000101101001011010010101 #
b1001 3
#7330000
b1010 *
b101000000110010101001001000100000000000000000000 +
1&
#7340000
0&
b100000011001010100100100010110100101101001010110 #
b10 "
b10 )
b10 $
b10 (
b1010 3
#7350000
b1011 *
b100000011001010100100100010000000000000000000000 +
1&
#7360000
0&
b1100101010010010001011010010110100101011010 #
b1011 3
#7370000
b1100 *
b1100101010010010001000000000000000000000000 +
1&
#7380000
0&
b110010101001001000101101001011010010101101000 #
b0 "
b0 )
b0 $
b0 (
b1100 3
#7390000
b1101 *
b110010101001001000100000000000000000000000000 +
1&
#7400000
0&
b11001010100100100010110100101101001010110100000 #
b1101 3
#7410000
b1110 *
b11001010100100100010000000000000000000000000000 +
1&
#7420000
0&
b100101010010010001011010010110100101011010000001 #
b1 "
b1 )
b1 $
b1 (
b1110 3
#7430000
b1111 *
b100101010010010001000000000000000000000000000000 +
1&
#7440000
0&
b10101001001000101101001011010010101101000000110 #
b10 "
b10 )
b10 $
b10 (
b1111 3
#7450000
b10000 *
b10101001001000100000000000000000000000000000000 +
1&
#7460000
0&
b10100100100010110100101101001010110100000011001 #
b1 "
b1 )
b1 $
b1 (
b10000 3
#7470000
b10001 *
b10100100100010000000000000000000000000000000000 +
1&
#7480000
0&
b10010010001011010010110100101011010000001100101 #
b10001 3
#7490000
b10010 *
b10010010001000000000000000000000000000000000000 +
1&
#7500000
0&
b1001000101101001011010010101101000000110010101 #
b10010 3
#7510000
b10011 *
b1001000100000000000000000000000000000000000000 +
1&
#7520000
0&
b100100010110100101101001010110100000011001010100 #
b0 "
b0 )
b0 $
b0 (
b10011 3
#7530000
b10100 *
b100100010000000000000000000000000000000000000000 +
1&
#7540000
0&
b10001011010010110100101011010000001100101010010 #
b10 "
b10 )
b10 $
b10 (
b10100 3
#7550000
b10101 *
b10001000000000000000000000000000000000000000000 +
1&
#7560000
0&
b101101001011010010101101000000110010101001001 #
b1 "
b1 )
b1 $
b1 (
b10101 3
#7570000
b10110 *
b100000000000000000000000000000000000000000000 +
1&
#7580000
0&
b10110100101101001010110100000011001010100100100 #
b0 "
b0 )
b0 $
b0 (
b10110 3
#7590000
b10111 *
b10000000000000000000000000000000000000000000000 +
1&
#7600000
0&
b11010010110100101011010000001100101010010010001 #
b1 "
b1 )
b1 $
b1 (
b10111 3
#7610000
b11 ,
b0 *
b0 +
1&
#7620000
0&
b0 "
b0 )
b0 $
b0 (
b0 4
b11000 3
#7630000
b1 *
1&
#7640000
0&
b1 4
#7650000
b10 *
1&
#7660000
0&
b10 4
#7670000
b11 *
1&
#7680000
0&
b11 4
#7690000
b100 *
1&
#7700000
0&
b100 4
#7710000
b101 *
1&
#7720000
0&
b101 4
#7730000
b110 *
1&
#7740000
0&
b110 4
#7750000
b111 *
1&
#7760000
0&
b111 4
#7770000
b1000 *
1&
#7780000
0&
b1000 4
#7790000
b1001 *
1&
#7800000
0&
b1001 4
#7810000
b1010 *
1&
#7820000
0&
b1010 4
#7830000
b1011 *
1&
#7840000
0&
b1011 4
#7850000
b1100 *
1&
#7860000
0&
b1100 4
#7870000
b1101 *
1&
#7880000
0&
b1101 4
#7890000
b1110 *
1&
#7900000
0&
b1110 4
#7910000
b1111 *
1&
#7920000
0&
b1111 4
#7930000
b10000 *
1&
#7940000
0&
b10000 4
#7950000
b10001 *
1&
#7960000
0&
b10001 4
#7970000
b10010 *
1&
#7980000
0&
b10010 4
#7990000
b10011 *
1&
#8000000
0&
b10011 4
#8010000
b10100 *
1&
#8020000
0&
b10100 4
#8030000
b10101 *
1&
#8040000
0&
b10101 4
#8050000
b10110 *
1&
#8060000
0&
b10110 4
#8070000
b10111 *
1&
#8080000
0&
b10111 4
#8090000
b11000 *
1&
#8100000
0&
b11000 4
#8110000
b11001 *
1&
#8120000
0&
b11001 4
#8130000
b11010 *
1&
#8140000
0&
b11010 4
#8150000
b11011 *
1&
#8160000
0&
b11011 4
#8170000
b11100 *
1&
#8180000
0&
b11100 4
#8190000
b11101 *
1&
#8200000
0&
b11101 4
#8210000
b11110 *
1&
#8220000
0&
b11110 4
#8230000
b11111 *
1&
#8240000
0&
b11111 4
#8250000
1!
b100 ,
b0 *
1&
#8260000
0&
b10 "
b10 )
b10 $
b10 (
b0 5
b100000 4
#8270000
1&
#8280000
0&
b1 5
#8290000
1&
#8300000
0&
b10 5
#8310000
1&
#8320000
0&
b11 5
#8330000
1&
#8340000
0&
b100 5
#8350000
1&
#8360000
0&
b101 5
#8370000
1&
#8380000
0&
b110 5
#8390000
1&
#8400000
0&
b111 5
#8410000
1&
#8420000
0&
b1000 5
#8430000
1&
#8440000
0&
b1001 5
#8450000
1&
#8460000
0&
b1010 5
#8470000
1&
#8480000
0&
b1011 5
#8490000
1&
#8500000
0&
b1100 5
#8510000
1&
#8520000
0&
b1101 5
#8530000
1&
#8540000
0&
b1110 5
#8550000
1&
#8560000
0&
b1111 5
#8570000
1&
#8580000
0&
b10000 5
#8590000
1&
#8600000
0&
b10001 5
#8610000
1&
#8620000
0&
b10010 5
#8630000
1&
#8640000
0&
b10011 5
#8650000
1&
#8660000
0&
b10100 5
#8670000
1&
#8680000
0&
b10101 5
#8690000
1&
#8700000
0&
b10110 5
#8710000
1&
#8720000
0&
b10111 5
#8730000
1&
#8740000
0&
b11000 5
#8750000
1&
#8760000
0&
b11001 5
#8770000
1&
#8780000
0&
b11010 5
#8790000
1&
#8800000
0&
b11011 5
#8810000
1&
#8820000
0&
b11100 5
#8830000
1&
#8840000
0&
b11101 5
#8850000
1&
#8860000
0&
b11110 5
#8870000
1&
#8880000
0&
b11111 5
#8890000
1&
#8900000
0&
b100000 5
#8910000
1&
#8920000
0&
b100001 5
#8930000
1&
#8940000
0&
b100010 5
#8950000
1&
#8960000
0&
b100011 5
#8970000
1&
#8980000
0&
b100100 5
#8990000
1&
#9000000
0&
b100101 5
#9010000
1&
#9020000
0&
b100110 5
#9030000
1&
#9040000
0&
b100111 5
#9050000
1&
#9060000
0&
b101000 5
#9070000
1&
#9080000
0&
b101001 5
#9090000
1&
#9100000
0&
b101010 5
#9110000
1&
#9120000
0&
b101011 5
#9130000
1&
#9140000
0&
b101100 5
#9150000
1&
