src/parser.sv
`default_nettype none
`timescale 1ns / 1ps

import proctypes::*;

// 1 stage pipeline - register on output
module parser (
    input wire clk,
    input wire rst,
    input wire [31:0] instruction,
    input wire valid_in,
    output logic valid_out,
    output DecodedInst dInst
);
    logic nextShapeData;

    DecodedInst nextDInst = DecodedInst'(0);
    OpCode opcode = OpCode'(0);
    logic [1:0] func;

    always @(*) begin
        if (nextShapeData) begin
            nextDInst.iType = opShapeData;
            nextDInst.data  = instruction[31:16];
            nextDInst.data2 = instruction[15:0];
        end else begin
            opcode = OpCode'(instruction[2:0]);

            case (opcode)
                ocFType: begin
                    func = instruction[10:9];
                    if (func == 2'b00) begin
                        nextDInst.iType = opRender;
                    end else begin
                        nextDInst.iType = opFrame;
                    end
                end
                ocCType: begin
                    nextDInst.iType = opCameraSet;
                    nextDInst.prop = instruction[15:11];
                    nextDInst.data = instruction[31:16];
                end
                ocLType: begin
                    nextDInst.iType = opLightSet;
                    nextDInst.lIndex = instruction[8:3];
                    nextDInst.prop = instruction[15:11];
                    nextDInst.data = instruction[31:16];
                end
                ocSIType: begin
                    nextDInst.iType = opShapeInit;
                    nextDInst.sIndex = {instruction[31:16], instruction[5:3]};
                    nextDInst.sType = instruction[15:11];
                end
                ocSEType: begin
                    nextDInst.iType = opShapeSet;
                    nextDInst.sIndex = {instruction[31:16], instruction[5:3]};
                    nextDInst.prop = instruction[15:11];
                    nextDInst.prop2 = instruction[10:6];
                end
                default: begin
                    nextDInst.iType = opUnsupported;
                end
            endcase
        end 
    end

    always_ff @( posedge clk ) begin 
        if (rst) begin
            nextShapeData <= 1'b0;
            valid_out <= 1'b0;
            dInst <= 0;
        end else begin
            valid_out <= valid_in;
            dInst <= nextDInst;
            if (valid_in && (nextDInst.iType == opShapeSet)) begin
                nextShapeData <= 1'b1;
            end else if (valid_in) begin
                nextShapeData <= 1'b0;
            end
        end
    end
endmodule

`default_nettype wire

sim/parser_tb.sv
`default_nettype none
`timescale 1ns / 1ps

import proctypes::*;

module parser_tb;
    logic clk;
    logic rst;
    logic [31:0] instruction;
    logic valid_in;

    logic valid_out;
    DecodedInst dInst;

    parser ip(
        .clk(clk),
        .rst(rst),
        .instruction(instruction),
        .valid_in(valid_in),
        .valid_out(valid_out),
        .dInst(dInst)
    );

    
    // 100 MHz clock
    always begin
        #5;
        clk = !clk;
    end

    initial begin
        $dumpfile("parser.vcd");
        $dumpvars(0, parser_tb);
        $display("Starting Sim");

        clk = 1'b0;
        rst = 1'b0;
        valid_in = 1'b0;
        #10;
        #10;
        rst = 1'b1;
        #10;
        rst = 1'b0;
        #10;
        #10;

        // TC1 : New render
        instruction = 32'b0000_0000_0000_0000_0000_0000_0000_0000;
        valid_in = 1'b1;
        #10;
        $display("-----------------------------");
        $display("Instruction type: \t %19b", dInst.iType);
        $display("Light index: \t\t %19b", dInst.lIndex);
        $display("Shape index:\t\t %19b", dInst.sIndex);
        $display("Shape type: \t\t %19b", dInst.sType);
        $display("Property 1: \t\t %19b", dInst.prop);
        $display("Property 2: \t\t %19b", dInst.prop2);
        $display("Data 1: \t\t %19b", dInst.data);
        $display("Data 2: \t\t %19b", dInst.data2);
        
        // TC2: New frame
        instruction = 32'b0000_0000_0000_0000_0000_0010_0000_0000;
        valid_in = 1'b1;
        #10;
        $display("-----------------------------");
        $display("Instruction type: \t %19b", dInst.iType);
        $display("Light index: \t\t %19b", dInst.lIndex);
        $display("Shape index:\t\t %19b", dInst.sIndex);
        $display("Shape type: \t\t %19b", dInst.sType);
        $display("Property 1: \t\t %19b", dInst.prop);
        $display("Property 2: \t\t %19b", dInst.prop2);
        $display("Data 1: \t\t %19b", dInst.data);
        $display("Data 2: \t\t %19b", dInst.data2);

        // TC3: Camera set x-location to 16'b0101_0101_0101_1111
        instruction = 32'b0101_0101_0101_1111_00001_00000000_001;
        valid_in = 1'b1;
        #10;
        $display("-----------------------------");
        $display("Instruction type: \t %19b", dInst.iType);
        $display("Light index: \t\t %19b", dInst.lIndex);
        $display("Shape index:\t\t %19b", dInst.sIndex);
        $display("Shape type: \t\t %19b", dInst.sType);
        $display("Property 1: \t\t %19b", dInst.prop);
        $display("Property 2: \t\t %19b", dInst.prop2);
        $display("Data 1: \t\t %19b", dInst.data);
        $display("Data 2: \t\t %19b", dInst.data2);

        #10;
        $display("\nFinishing Sim");
        $finish;
    end
endmodule

`default_nettype wire

parser.vcd
$date
	Sat Nov 26 20:10:33 2022
$end
$version
	Icarus Verilog
$end
$timescale
	1ps
$end
$scope module parser_tb $end
$var wire 1 ! valid_out $end
$var wire 75 " dInst [74:0] $end
$var reg 1 # clk $end
$var reg 32 $ instruction [31:0] $end
$var reg 1 % rst $end
$var reg 1 & valid_in $end
$scope module ip $end
$var wire 1 # clk $end
$var wire 32 ' instruction [31:0] $end
$var wire 1 % rst $end
$var wire 1 & valid_in $end
$var reg 75 ( dInst [74:0] $end
$var reg 2 ) func [1:0] $end
$var reg 75 * nextDInst [74:0] $end
$var reg 1 + nextShapeData $end
$var reg 3 , opcode [2:0] $end
$var reg 1 ! valid_out $end
$upscope $end
$upscope $end
$enddefinitions $end
#0
$dumpvars
b0 ,
x+
b0 *
bx )
bx (
bx '
0&
0%
bx $
0#
bx "
x!
$end
#5000
b0 "
b0 (
0!
1#
#10000
0#
#15000
1#
#20000
0#
1%
#25000
bx ,
0+
1#
#30000
0#
0%
#35000
1#
#40000
0#
#45000
1#
#50000
b1000000000000000000000000000000000000000000000000000000000000000000000000 *
b0 )
b0 ,
0#
1&
b0 $
b0 '
#55000
b1000000000000000000000000000000000000000000000000000000000000000000000000 "
b1000000000000000000000000000000000000000000000000000000000000000000000000 (
1!
1#
#60000
b10000000000000000000000000000000000000000000000000000000000000000000000000 *
b1 )
0#
b1000000000 $
b1000000000 '
#65000
b10000000000000000000000000000000000000000000000000000000000000000000000000 "
b10000000000000000000000000000000000000000000000000000000000000000000000000 (
1#
#70000
b11000000000000000000000000000000000010000001010101010111110000000000000000 *
b1 ,
0#
b1010101010111110000100000000001 $
b1010101010111110000100000000001 '
#75000
b11000000000000000000000000000000000010000001010101010111110000000000000000 "
b11000000000000000000000000000000000010000001010101010111110000000000000000 (
1#
