src/pipe.sv
`default_nettype none
module pipe #(
    LENGTH = 1
) (
    input  wire  clk,
    input  wire  rst,
    input  wire  in,
    output logic out,
    output logic [LENGTH-1:0] line
);

  logic temp;
  assign out  = line[LENGTH-1];
  assign temp = line << 1;

  always_ff @(posedge clk) begin
    if (rst) begin
      line <= 0;
    end else begin
    line[0] <= in;
    for (int i = 0; i < LENGTH - 1; i++ ) begin
        line[i + 1] <= line[i];
    end

    end
  end
endmodule
`default_nettype wire

sim/pipe_tb.sv
`timescale 1ns / 1ps
//
`default_nettype none

module pipe_tb;

  //make logics for inputs and outputs!
  logic rst;
  logic clk;
  logic pipe_in;
  logic pipe_out;

  pipe #(.LENGTH(10)) p (
      .rst(rst),
      .clk(clk),
      .in (pipe_in),
      .out(pipe_out)
  );

  //   always begin
  //     #6;  //6ns switch: period of 12ns -> ~81.25 MHz
  //     clk = !clk;
  //   end

  always begin
    #2.5;  //2.5 switch: period 5 ns -> 200Hz
    clk = !clk;
  end

  //initial block...this is our test simulation
  initial begin
    $dumpfile("pipe.vcd");  //file to store value change dump (vcd)
    $dumpvars(0, pipe_tb);  //store everything at the current level and below
    $display("Starting Sim");  //print nice message
    clk = 0;
    rst = 0;
    pipe_in = 0;
    // output_signal_dest_clk = 1;
    #22.5  //wait
      rst = 1;
    #20;  //hold
    rst = 0;
    #20;

    #100; 
    pipe_in = 1;
    #12;
    pipe_in = 0;
    #240
    pipe_in = 1;
    #36;
    pipe_in = 0;

    #600;
    $finish;

  end
endmodule  //counter_tb

`default_nettype wire

pipe.vcd
$date
	Wed Nov 30 02:39:15 2022
$end
$version
	Icarus Verilog
$end
$timescale
	1ps
$end
$scope module pipe_tb $end
$var wire 1 ! pipe_out $end
$var reg 1 " clk $end
$var reg 1 # pipe_in $end
$var reg 1 $ rst $end
$scope module p $end
$var wire 1 " clk $end
$var wire 1 # in $end
$var wire 1 $ rst $end
$var wire 1 % temp $end
$var wire 1 ! out $end
$var parameter 32 & LENGTH $end
$var reg 10 ' line [9:0] $end
$scope begin $ivl_for_loop0 $end
$var integer 32 ( i [31:0] $end
$upscope $end
$upscope $end
$upscope $end
$enddefinitions $end
$comment Show the parameter values. $end
$dumpall
b1010 &
$end
#0
$dumpvars
b0 (
bx '
0%
0$
0#
0"
x!
$end
#2500
bx0 '
b1001 (
1"
#5000
0"
#7500
bx00 '
b1001 (
1"
#10000
0"
#12500
bx000 '
b1001 (
1"
#15000
0"
#17500
bx0000 '
b1001 (
1"
#20000
0"
#22500
0!
b0 '
1"
1$
#25000
0"
#27500
1"
#30000
0"
#32500
1"
#35000
0"
#37500
1"
#40000
0"
#42500
b1001 (
1"
0$
#45000
0"
#47500
b1001 (
1"
#50000
0"
#52500
b1001 (
1"
#55000
0"
#57500
b1001 (
1"
#60000
0"
#62500
b1001 (
1"
#65000
0"
#67500
b1001 (
1"
#70000
0"
#72500
b1001 (
1"
#75000
0"
#77500
b1001 (
1"
#80000
0"
#82500
b1001 (
1"
#85000
0"
#87500
b1001 (
1"
#90000
0"
#92500
b1001 (
1"
#95000
0"
#97500
b1001 (
1"
#100000
0"
#102500
b1001 (
1"
#105000
0"
#107500
b1001 (
1"
#110000
0"
#112500
b1001 (
1"
#115000
0"
#117500
b1001 (
1"
#120000
0"
#122500
b1001 (
1"
#125000
0"
#127500
b1001 (
1"
#130000
0"
#132500
b1001 (
1"
#135000
0"
#137500
b1001 (
1"
#140000
0"
#142500
b1001 (
1"
#145000
0"
#147500
b1001 (
1"
#150000
0"
#152500
b1001 (
1"
#155000
0"
#157500
b1001 (
1"
#160000
0"
#162500
b1 '
b1001 (
1"
1#
#165000
0"
#167500
b11 '
b1001 (
1"
#170000
0"
#172500
b111 '
b1001 (
1"
#174500
0#
#175000
0"
#177500
b1110 '
b1001 (
1"
#180000
0"
#182500
b11100 '
b1001 (
1"
#185000
0"
#187500
b111000 '
b1001 (
1"
#190000
0"
#192500
b1110000 '
b1001 (
1"
#195000
0"
#197500
b11100000 '
b1001 (
1"
#200000
0"
#202500
b111000000 '
b1001 (
1"
#205000
0"
#207500
1!
b1110000000 '
b1001 (
1"
#210000
0"
#212500
b1100000000 '
b1001 (
1"
#215000
0"
#217500
b1000000000 '
b1001 (
1"
#220000
0"
#222500
0!
b0 '
b1001 (
1"
#225000
0"
#227500
b1001 (
1"
#230000
0"
#232500
b1001 (
1"
#235000
0"
#237500
b1001 (
1"
#240000
0"
#242500
b1001 (
1"
#245000
0"
#247500
b1001 (
1"
#250000
0"
#252500
b1001 (
1"
#255000
0"
#257500
b1001 (
1"
#260000
0"
#262500
b1001 (
1"
#265000
0"
#267500
b1001 (
1"
#270000
0"
#272500
b1001 (
1"
#275000
0"
#277500
b1001 (
1"
#280000
0"
#282500
b1001 (
1"
#285000
0"
#287500
b1001 (
1"
#290000
0"
#292500
b1001 (
1"
#295000
0"
#297500
b1001 (
1"
#300000
0"
#302500
b1001 (
1"
#305000
0"
#307500
b1001 (
1"
#310000
0"
#312500
b1001 (
1"
#315000
0"
#317500
b1001 (
1"
#320000
0"
#322500
b1001 (
1"
#325000
0"
#327500
b1001 (
1"
#330000
0"
#332500
b1001 (
1"
#335000
0"
#337500
b1001 (
1"
#340000
0"
#342500
b1001 (
1"
#345000
0"
#347500
b1001 (
1"
#350000
0"
#352500
b1001 (
1"
#355000
0"
#357500
b1001 (
1"
#360000
0"
#362500
b1001 (
1"
#365000
0"
#367500
b1001 (
1"
#370000
0"
#372500
b1001 (
1"
#375000
0"
#377500
b1001 (
1"
#380000
0"
#382500
b1001 (
1"
#385000
0"
#387500
b1001 (
1"
#390000
0"
#392500
b1001 (
1"
#395000
0"
#397500
b1001 (
1"
#400000
0"
#402500
b1001 (
1"
#405000
0"
#407500
b1001 (
1"
#410000
0"
#412500
b1001 (
1"
#414500
1#
#415000
0"
#417500
b1 '
b1001 (
1"
#420000
0"
#422500
b11 '
b1001 (
1"
#425000
0"
#427500
b111 '
b1001 (
1"
#430000
0"
#432500
b1111 '
b1001 (
1"
#435000
0"
#437500
b11111 '
b1001 (
1"
#440000
0"
#442500
b111111 '
b1001 (
1"
#445000
0"
#447500
b1111111 '
b1001 (
1"
#450000
0"
#450500
0#
#452500
b11111110 '
b1001 (
1"
#455000
0"
#457500
b111111100 '
b1001 (
1"
#460000
0"
#462500
1!
b1111111000 '
b1001 (
1"
#465000
0"
#467500
b1111110000 '
b1001 (
1"
#470000
0"
#472500
b1111100000 '
b1001 (
1"
#475000
0"
#477500
b1111000000 '
b1001 (
1"
#480000
0"
#482500
b1110000000 '
b1001 (
1"
#485000
0"
#487500
b1100000000 '
b1001 (
1"
#490000
0"
#492500
b1000000000 '
b1001 (
1"
#495000
0"
#497500
0!
b0 '
b1001 (
1"
#500000
0"
#502500
b1001 (
1"
#505000
0"
#507500
b1001 (
1"
#510000
0"
#512500
b1001 (
1"
#515000
0"
#517500
b1001 (
1"
#520000
0"
#522500
b1001 (
1"
#525000
0"
#527500
b1001 (
1"
#530000
0"
#532500
b1001 (
1"
#535000
0"
#537500
b1001 (
1"
#540000
0"
#542500
b1001 (
1"
#545000
0"
#547500
b1001 (
1"
#550000
0"
#552500
b1001 (
1"
#555000
0"
#557500
b1001 (
1"
#560000
0"
#562500
b1001 (
1"
#565000
0"
#567500
b1001 (
1"
#570000
0"
#572500
b1001 (
1"
#575000
0"
#577500
b1001 (
1"
#580000
0"
#582500
b1001 (
1"
#585000
0"
#587500
b1001 (
1"
#590000
0"
#592500
b1001 (
1"
#595000
0"
#597500
b1001 (
1"
#600000
0"
#602500
b1001 (
1"
#605000
0"
#607500
b1001 (
1"
#610000
0"
#612500
b1001 (
1"
#615000
0"
#617500
b1001 (
1"
#620000
0"
#622500
b1001 (
1"
#625000
0"
#627500
b1001 (
1"
#630000
0"
#632500
b1001 (
1"
#635000
0"
#637500
b1001 (
1"
#640000
0"
#642500
b1001 (
1"
#645000
0"
#647500
b1001 (
1"
#650000
0"
#652500
b1001 (
1"
#655000
0"
#657500
b1001 (
1"
#660000
0"
#662500
b1001 (
1"
#665000
0"
#667500
b1001 (
1"
#670000
0"
#672500
b1001 (
1"
#675000
0"
#677500
b1001 (
1"
#680000
0"
#682500
b1001 (
1"
#685000
0"
#687500
b1001 (
1"
#690000
0"
#692500
b1001 (
1"
#695000
0"
#697500
b1001 (
1"
#700000
0"
#702500
b1001 (
1"
#705000
0"
#707500
b1001 (
1"
#710000
0"
#712500
b1001 (
1"
#715000
0"
#717500
b1001 (
1"
#720000
0"
#722500
b1001 (
1"
#725000
0"
#727500
b1001 (
1"
#730000
0"
#732500
b1001 (
1"
#735000
0"
#737500
b1001 (
1"
#740000
0"
#742500
b1001 (
1"
#745000
0"
#747500
b1001 (
1"
#750000
0"
#752500
b1001 (
1"
#755000
0"
#757500
b1001 (
1"
#760000
0"
#762500
b1001 (
1"
#765000
0"
#767500
b1001 (
1"
#770000
0"
#772500
b1001 (
1"
#775000
0"
#777500
b1001 (
1"
#780000
0"
#782500
b1001 (
1"
#785000
0"
#787500
b1001 (
1"
#790000
0"
#792500
b1001 (
1"
#795000
0"
#797500
b1001 (
1"
#800000
0"
#802500
b1001 (
1"
#805000
0"
#807500
b1001 (
1"
#810000
0"
#812500
b1001 (
1"
#815000
0"
#817500
b1001 (
1"
#820000
0"
#822500
b1001 (
1"
#825000
0"
#827500
b1001 (
1"
#830000
0"
#832500
b1001 (
1"
#835000
0"
#837500
b1001 (
1"
#840000
0"
#842500
b1001 (
1"
#845000
0"
#847500
b1001 (
1"
#850000
0"
#852500
b1001 (
1"
#855000
0"
#857500
b1001 (
1"
#860000
0"
#862500
b1001 (
1"
#865000
0"
#867500
b1001 (
1"
#870000
0"
#872500
b1001 (
1"
#875000
0"
#877500
b1001 (
1"
#880000
0"
#882500
b1001 (
1"
#885000
0"
#887500
b1001 (
1"
#890000
0"
#892500
b1001 (
1"
#895000
0"
#897500
b1001 (
1"
#900000
0"
#902500
b1001 (
1"
#905000
0"
#907500
b1001 (
1"
#910000
0"
#912500
b1001 (
1"
#915000
0"
#917500
b1001 (
1"
#920000
0"
#922500
b1001 (
1"
#925000
0"
#927500
b1001 (
1"
#930000
0"
#932500
b1001 (
1"
#935000
0"
#937500
b1001 (
1"
#940000
0"
#942500
b1001 (
1"
#945000
0"
#947500
b1001 (
1"
#950000
0"
#952500
b1001 (
1"
#955000
0"
#957500
b1001 (
1"
#960000
0"
#962500
b1001 (
1"
#965000
0"
#967500
b1001 (
1"
#970000
0"
#972500
b1001 (
1"
#975000
0"
#977500
b1001 (
1"
#980000
0"
#982500
b1001 (
1"
#985000
0"
#987500
b1001 (
1"
#990000
0"
#992500
b1001 (
1"
#995000
0"
#997500
b1001 (
1"
#1000000
0"
#1002500
b1001 (
1"
#1005000
0"
#1007500
b1001 (
1"
#1010000
0"
#1012500
b1001 (
1"
#1015000
0"
#1017500
b1001 (
1"
#1020000
0"
#1022500
b1001 (
1"
#1025000
0"
#1027500
b1001 (
1"
#1030000
0"
#1032500
b1001 (
1"
#1035000
0"
#1037500
b1001 (
1"
#1040000
0"
#1042500
b1001 (
1"
#1045000
0"
#1047500
b1001 (
1"
